fitellipsoid/__init__.py
fitellipsoid/_widget.py
fitellipsoid/_widget_old.py
fitellipsoid/math_func.py
fitellipsoid/napari.yaml
fitellipsoid-0.0.6.dist-info/licenses/LICENSE
fitellipsoid-0.0.6.dist-info/METADATA
fitellipsoid-0.0.6.dist-info/WHEEL
fitellipsoid-0.0.6.dist-info/entry_points.txt
fitellipsoid-0.0.6.dist-info/top_level.txt
fitellipsoid-0.0.6.dist-info/RECORD
